league_connection/__init__.py
league_connection/connection.py
league_connection/exceptions.py
league_connection/info.py
league_connection-1.0.1.dist-info/LICENSE
league_connection-1.0.1.dist-info/METADATA
league_connection-1.0.1.dist-info/WHEEL
league_connection-1.0.1.dist-info/top_level.txt
league_connection-1.0.1.dist-info/RECORD
