Metadata-Version: 2.1
Name: league-connection
Version: 1.0.1
Summary: Python package to communicate to riot client and league client
Home-page: https://github.com/sandbox-pokhara/league-connection
Author: Pradish Bijukchhe
Author-email: pradishbijukchhe@gmail.com
License: UNKNOWN
Project-URL: Bug Tracker, https://github.com/sandbox-pokhara/league-connection/issues
Platform: UNKNOWN
Classifier: Programming Language :: Python :: 3
Classifier: License :: OSI Approved :: MIT License
Classifier: Operating System :: Microsoft :: Windows
Requires-Python: >=3.6
License-File: LICENSE
Requires-Dist: requests
